django_password_history/__init__.py
django_password_history/admin.py
django_password_history/apps.py
django_password_history/models.py
django_password_history/urls.py
django_password_history/views.py
django_password_history/migrations/0001_initial.py
django_password_history/migrations/0002_auto_20220831_2019.py
django_password_history/migrations/__init__.py
django_password_history/static/css/django_password_history.css
django_password_history/static/js/django_password_history.js
django_password_history/templates/django_password_history/base.html
django_password_history/test_utils/__init__.py
django_password_history/test_utils/test_app/__init__.py
django_password_history/test_utils/test_app/admin.py
django_password_history/test_utils/test_app/apps.py
django_password_history/test_utils/test_app/models.py
django_password_history/test_utils/test_app/migrations/__init__.py
django_password_history-1.0.8.dist-info/AUTHORS.rst
django_password_history-1.0.8.dist-info/LICENSE
django_password_history-1.0.8.dist-info/METADATA
django_password_history-1.0.8.dist-info/WHEEL
django_password_history-1.0.8.dist-info/top_level.txt
django_password_history-1.0.8.dist-info/RECORD
