Metadata-Version: 2.1
Name: django-password-history
Version: 1.0.8
Summary: Django module meant to allow django users to keep a history of their previously used passwords.
Home-page: https://github.com/Lenders-Cooperative/django-password-history
Author: Roderick Smith
Author-email: smithroderick17@gmail.com
License: BSD
Download-URL: https://github.com/Lenders-Cooperative/django-password-history/archive/refs/tags/vf.tar.gz
Keywords: django-password-history
Platform: UNKNOWN
Classifier: Framework :: Django :: 2.2
Classifier: Framework :: Django :: 3.0
Classifier: Framework :: Django :: 3.1
Classifier: Framework :: Django :: 3.2
Classifier: Framework :: Django :: 4.0
Classifier: Intended Audience :: Developers
Classifier: License :: OSI Approved :: BSD License
Classifier: Natural Language :: English
Classifier: Programming Language :: Python :: 3
Classifier: Programming Language :: Python :: 3.5
Classifier: Programming Language :: Python :: 3.6
Classifier: Programming Language :: Python :: 3.7
Classifier: Programming Language :: Python :: 3.8
Classifier: Programming Language :: Python :: 3.9
Classifier: Programming Language :: Python :: 3.10
